MANIFEST.in
README.md
setup.cfg
setup.py
crisp/__init__.py
crisp/calibration.py
crisp/camera.py
crisp/cli.py
crisp/imu.py
crisp/l3g4200d.py
crisp/pose.py
crisp/ransac.py
crisp/remove_slp.py
crisp/rotations.py
crisp/stream.py
crisp/timesync.py
crisp/tracking.py
crisp/videoslice.py
crisp/znccpyr.py
crisp.egg-info/PKG-INFO
crisp.egg-info/SOURCES.txt
crisp.egg-info/dependency_links.txt
crisp.egg-info/pbr.json
crisp.egg-info/requires.txt
crisp.egg-info/top_level.txt
crisp/fastintegrate/fastintegrate.c
crisp/fastintegrate/fastintegrate.pyx