Metadata-Version: 1.1
Name: crisp
Version: 2.2
Summary: Camera-to-IMU calibration and synchronization toolkit
Home-page: https://github.com/hovren/crisp
Author: Hannes Ovrén
Author-email: hannes.ovren@liu.se
License: GPL
Keywords: gyroscope gyro camera imu calibration synchronization
Platform: UNKNOWN
Classifier: Development Status :: 4 - Beta
Classifier: Intended Audience :: Science/Research
Classifier: Topic :: Scientific/Engineering
Classifier: License :: OSI Approved :: GNU General Public License (GPL)
Classifier: Programming Language :: Python :: 2.7
Classifier: Programming Language :: Python :: 3.4
Requires: numpy
Requires: scipy
Requires: matplotlib
